odoo/addons/partner_salesperson_propagate/README.rst
odoo/addons/partner_salesperson_propagate/__init__.py
odoo/addons/partner_salesperson_propagate/__manifest__.py
odoo/addons/partner_salesperson_propagate/i18n/it.po
odoo/addons/partner_salesperson_propagate/i18n/partner_salesperson_propagate.pot
odoo/addons/partner_salesperson_propagate/models/__init__.py
odoo/addons/partner_salesperson_propagate/models/res_partner.py
odoo/addons/partner_salesperson_propagate/readme/CONTRIBUTORS.rst
odoo/addons/partner_salesperson_propagate/readme/DESCRIPTION.rst
odoo/addons/partner_salesperson_propagate/static/description/icon.png
odoo/addons/partner_salesperson_propagate/static/description/index.html
odoo/addons/partner_salesperson_propagate/tests/__init__.py
odoo/addons/partner_salesperson_propagate/tests/test_partner_salesperson_propagate.py
odoo_addon_partner_salesperson_propagate-16.0.1.0.0.4.dist-info/METADATA
odoo_addon_partner_salesperson_propagate-16.0.1.0.0.4.dist-info/WHEEL
odoo_addon_partner_salesperson_propagate-16.0.1.0.0.4.dist-info/top_level.txt
odoo_addon_partner_salesperson_propagate-16.0.1.0.0.4.dist-info/RECORD
